{
  "dimension": [
    {
      "conceptName": "analytics.trafficChannel",
      "displayName": "Default Channel Grouping",
      "enumValues": [],
      "externalName": "ga:channelGrouping"
    }
  ],
  "metric": [
    {
      "conceptName": "analytics.totalVisitors",
      "displayName": "Users",
      "enumValues": [],
      "smallerValueBetter": false,
      "helpTopicId": 2630986,
      "externalName": "ga:users"
    },
    {
      "conceptName": "analytics.newVisits",
      "displayName": "New Users",
      "enumValues": [],
      "smallerValueBetter": false,
      "helpTopicId": 2630913,
      "externalName": "ga:newUsers"
    },
    {
      "conceptName": "analytics.visits",
      "displayName": "Sessions",
      "enumValues": [],
      "smallerValueBetter": false,
      "helpTopicId": 2631008,
      "externalName": "ga:sessions"
    },
    {
      "conceptName": "analytics.bounceRate",
      "displayName": "Bounce Rate",
      "enumValues": [],
      "smallerValueBetter": true,
      "helpTopicId": 1006257,
      "externalName": "ga:bounceRate"
    },
    {
      "conceptName": "analytics.avgPageviews",
      "displayName": "Pages / Session",
      "enumValues": [],
      "smallerValueBetter": false,
      "helpTopicId": 1006251,
      "externalName": "ga:pageviewsPerSession"
    },
    {
      "conceptName": "analytics.avgSessionTime",
      "displayName": "Avg. Session Duration",
      "enumValues": [],
      "smallerValueBetter": false,
      "helpTopicId": 2632799,
      "externalName": "ga:avgSessionDuration"
    },
    {
      "conceptName": "analytics.goalConversionRate",
      "displayName": "Goal Conversion Rate",
      "enumValues": [],
      "smallerValueBetter": false,
      "helpTopicId": 1708791,
      "externalName": "ga:goalConversionRateAll"
    },
    {
      "conceptName": "analytics.goalCompletionsAll",
      "displayName": "Goal Completions",
      "enumValues": [],
      "smallerValueBetter": false,
      "helpTopicId": 1006273,
      "externalName": "ga:goalCompletionsAll"
    },
    {
      "conceptName": "analytics.goalValueAll",
      "displayName": "Goal Value",
      "enumValues": [],
      "smallerValueBetter": false,
      "helpTopicId": 1006275,
      "externalName": "ga:goalValueAll"
    }
  ],
  "secondaryDimensions": [
    "analytics.deviceCategory",
    "analytics.medium",
    "analytics.source",
    "analytics.sourceMedium",
    "analytics.campaign",
    "analytics.eventAction",
    "analytics.eventLabel",
    "analytics.eventCategory",
    "analytics.landingPagePath",
    "analytics.pagePath"
  ]
}